whale/__init__.py
whale/engine/__init__.py
whale/engine/base_engine.py
whale/engine/presto_engine.py
whale/engine/sql_alchemy_engine.py
whale/engine/mixins/__init__.py
whale/engine/mixins/presto_commands_mixin.py
whale/extractor/__init__.py
whale/extractor/amundsen_neo4j_metadata_extractor.py
whale/extractor/base_bigquery_extractor.py
whale/extractor/bigquery_metadata_extractor.py
whale/extractor/bigquery_watermark_extractor.py
whale/extractor/glue_extractor.py
whale/extractor/postgres_metadata_extractor.py
whale/extractor/presto_loop_extractor.py
whale/extractor/presto_table_metadata_extractor.py
whale/extractor/snowflake_metadata_extractor.py
whale/extractor/spanner_metadata_extractor.py
whale/extractor/splice_machine_metadata_extractor.py
whale/extractor/ugc_runner.py
whale/loader/__init__.py
whale/loader/whale_loader.py
whale/models/__init__.py
whale/models/connection_config.py
whale/models/metric_value.py
whale/models/presto_watermark.py
whale/models/table_manifest.py
whale/models/table_metadata.py
whale/task/__init__.py
whale/transformer/__init__.py
whale/utils/__init__.py
whale/utils/config.py
whale/utils/extractor_wrappers.py
whale/utils/markdown_delimiters.py
whale/utils/neo4j.py
whale/utils/parsers.py
whale/utils/paths.py
whale/utils/sql.py
whale_pipelines-1.5.1.dist-info/METADATA
whale_pipelines-1.5.1.dist-info/WHEEL
whale_pipelines-1.5.1.dist-info/top_level.txt
whale_pipelines-1.5.1.dist-info/RECORD
