Metadata-Version: 2.1
Name: whale-pipelines
Version: 1.5.1
Summary: A pared-down metadata scraper + SQL runner.
Home-page: https://github.com/dataframehq/whale
Author: Robert Yi
Author-email: robert@ryi.me
License: UNKNOWN
Platform: UNKNOWN
Requires-Python: >=3.6
Requires-Dist: aadict
Requires-Dist: amundsen-databuilder
Requires-Dist: asn1crypto
Requires-Dist: asset
Requires-Dist: azure-common
Requires-Dist: azure-core
Requires-Dist: azure-storage-blob
Requires-Dist: boto3
Requires-Dist: botocore
Requires-Dist: cachetools
Requires-Dist: certifi
Requires-Dist: cffi
Requires-Dist: chardet
Requires-Dist: colored
Requires-Dist: cryptography
Requires-Dist: elasticsearch
Requires-Dist: future
Requires-Dist: globre
Requires-Dist: google-api-core
Requires-Dist: google-api-python-client
Requires-Dist: google-auth
Requires-Dist: google-auth-httplib2
Requires-Dist: google-auth-oauthlib
Requires-Dist: google-cloud-bigquery
Requires-Dist: google-cloud-core
Requires-Dist: google-cloud-datacatalog
Requires-Dist: google-cloud-spanner
Requires-Dist: google-crc32c
Requires-Dist: google-resumable-media
Requires-Dist: googleapis-common-protos
Requires-Dist: grpcio
Requires-Dist: grpcio-gcp
Requires-Dist: httplib2
Requires-Dist: idna
Requires-Dist: isodate
Requires-Dist: Jinja2
Requires-Dist: jmespath
Requires-Dist: msrest
Requires-Dist: neo4j-driver
Requires-Dist: neobolt
Requires-Dist: neotime
Requires-Dist: numpy
Requires-Dist: oauthlib
Requires-Dist: oscrypto
Requires-Dist: pandas
Requires-Dist: proto-plus
Requires-Dist: protobuf
Requires-Dist: psycopg2-binary
Requires-Dist: pyasn1
Requires-Dist: pyasn1-modules
Requires-Dist: pybigquery
Requires-Dist: pycparser
Requires-Dist: pycryptodomex
Requires-Dist: PyHive
Requires-Dist: pyhocon
Requires-Dist: PyJWT
Requires-Dist: pyOpenSSL
Requires-Dist: pyparsing
Requires-Dist: python-dateutil
Requires-Dist: pytz
Requires-Dist: PyYAML
Requires-Dist: requests
Requires-Dist: requests-oauthlib
Requires-Dist: retrying
Requires-Dist: rsa
Requires-Dist: s3transfer
Requires-Dist: six
Requires-Dist: snowflake-connector-python
Requires-Dist: snowflake-sqlalchemy
Requires-Dist: SQLAlchemy
Requires-Dist: statsd
Requires-Dist: termcolor
Requires-Dist: Unidecode
Requires-Dist: uritemplate
Requires-Dist: urllib3
